garlic/__init__.py
garlic/base_event.py
garlic/event_bus.py
garlic/garlic.py
garlic/protocol.py
garlic/subscriber.py
garlic/types.py
garlic/utils.py
garlic-0.5.0.dist-info/LICENSE
garlic-0.5.0.dist-info/METADATA
garlic-0.5.0.dist-info/WHEEL
garlic-0.5.0.dist-info/RECORD
