Metadata-Version: 2.1
Name: garlic
Version: 0.5.0
Summary: Create a event driven architecture with garlic improve your development experience
Home-page: https://github.com/Sancer/garlic
License: MIT
Author: Uriel Reina Abadía
Author-email: urielreina@gmail.com
Requires-Python: >=3.9,<4.0
Classifier: License :: OSI Approved :: MIT License
Classifier: Programming Language :: Python :: 3
Classifier: Programming Language :: Python :: 3.9
Classifier: Programming Language :: Python :: 3.10
Classifier: Programming Language :: Python :: 3.11
Requires-Dist: pika (>=1.3.2,<2.0.0)
Requires-Dist: pydantic (>=2.1.1,<3.0.0)
Project-URL: Repository, https://github.com/Sancer/garlic
